README.md
setup.py
PyEEGLab.egg-info/PKG-INFO
PyEEGLab.egg-info/SOURCES.txt
PyEEGLab.egg-info/dependency_links.txt
PyEEGLab.egg-info/requires.txt
PyEEGLab.egg-info/top_level.txt
pyeeglab/__init__.py
pyeeglab/dataset/__init__.py
pyeeglab/dataset/annotation.py
pyeeglab/dataset/dataset.py
pyeeglab/dataset/declarative_base.py
pyeeglab/dataset/file.py
pyeeglab/dataset/metadata.py
pyeeglab/dataset/physionet/__init__.py
pyeeglab/dataset/physionet/chbmit_dataset.py
pyeeglab/dataset/physionet/eegmmidb_dataset.py
pyeeglab/dataset/physionet/utils.py
pyeeglab/dataset/tuh_eeg/__init__.py
pyeeglab/dataset/tuh_eeg/abnormal_dataset.py
pyeeglab/dataset/tuh_eeg/artifact_dataset.py
pyeeglab/dataset/tuh_eeg/seizure_dataset.py
pyeeglab/dataset/tuh_eeg/utils.py
pyeeglab/pipeline/__init__.py
pyeeglab/pipeline/pipeline.py
pyeeglab/pipeline/preprocessor.py
pyeeglab/preprocess/__init__.py
pyeeglab/preprocess/features/__init__.py
pyeeglab/preprocess/features/brain_connectivity.py
pyeeglab/preprocess/features/stat_features.py
pyeeglab/preprocess/signal/__init__.py
pyeeglab/preprocess/signal/channel_selector.py
pyeeglab/preprocess/signal/filter_selector.py
pyeeglab/preprocess/signal/frequency_selector.py
pyeeglab/preprocess/signal/normalization.py
pyeeglab/preprocess/transform/__init__.py
pyeeglab/preprocess/transform/data_converter.py
pyeeglab/preprocess/transform/frame_generator.py