Metadata-Version: 2.1
Name: PyEEGLab
Version: 0.10.0
Summary: Analyze and manipulate EEG data using PyEEGLab
Home-page: https://github.com/AlessioZanga/PyEEGLab
Author: Alessio Zanga
Author-email: alessio.zanga@outlook.it
License: GNU GENERAL PUBLIC LICENSE - Version 3, 29 June 2007
Platform: Environment :: Console
Platform: Operating System :: POSIX :: Linux
Platform: Operating System :: Microsoft :: Windows :: Windows 10
Platform: Operating System :: MacOS
Classifier: Development Status :: 4 - Beta
Classifier: Intended Audience :: Science/Research
Classifier: License :: OSI Approved :: GNU General Public License v3 (GPLv3)
Classifier: Programming Language :: Python :: 3.6
Classifier: Programming Language :: Python :: 3.7
Classifier: Programming Language :: Python :: 3.8
Classifier: Topic :: Scientific/Engineering :: Human Machine Interfaces
Classifier: Topic :: Scientific/Engineering :: Medical Science Apps.
Classifier: Topic :: Software Development :: Libraries :: Python Modules
